fastapi_gcp_tasks/__init__.py
fastapi_gcp_tasks/decorators.py
fastapi_gcp_tasks/delayed_route.py
fastapi_gcp_tasks/delayer.py
fastapi_gcp_tasks/dependencies.py
fastapi_gcp_tasks/exception.py
fastapi_gcp_tasks/hooks.py
fastapi_gcp_tasks/requester.py
fastapi_gcp_tasks/scheduled_route.py
fastapi_gcp_tasks/scheduler.py
fastapi_gcp_tasks/utils.py
fastapi_gcp_tasks-0.1.1.dist-info/LICENSE
fastapi_gcp_tasks-0.1.1.dist-info/METADATA
fastapi_gcp_tasks-0.1.1.dist-info/WHEEL
fastapi_gcp_tasks-0.1.1.dist-info/RECORD
