Metadata-Version: 2.1
Name: fastapi-gcp-tasks
Version: 0.1.1
Summary: Trigger delayed Cloud Tasks from FastAPI
License: MIT
Author: Team Simplify
Author-email: oss@simplify.jobs
Requires-Python: >=3.11,<3.14
Classifier: License :: OSI Approved :: MIT License
Classifier: Programming Language :: Python :: 3
Classifier: Programming Language :: Python :: 3.11
Classifier: Programming Language :: Python :: 3.12
Requires-Dist: fastapi (>=0.110.0,<0.120.0)
Requires-Dist: google-cloud-scheduler (>=2.13.3,<2.20.0)
Requires-Dist: google-cloud-tasks (>=2.16.3,<2.20.0)
